.gitignore
LICENSE
README.md
setup.py
open_request_core/__init__.py
open_request_core/aiohttp_client.py
open_request_core/exception.py
open_request_core/grpc_client.py
open_request_core/grpc_request.py
open_request_core/http_client.py
open_request_core/http_request.py
open_request_core/http_response.py
open_request_core/requests_client.py
open_request_core.egg-info/PKG-INFO
open_request_core.egg-info/SOURCES.txt
open_request_core.egg-info/dependency_links.txt
open_request_core.egg-info/requires.txt
open_request_core.egg-info/top_level.txt