Metadata-Version: 2.1
Name: open-request-core
Version: 3.0.0
Summary: This is the core module of standard use for requests.
Home-page: https://github.com/meanstrong/open-request-core
Author: Rocky Peng
Author-email: rockypengchina@outlook.com
Maintainer: Rocky Peng
Maintainer-email: rockypengchina@outlook.com
License: Apache 2.0
Platform: any
Classifier: Programming Language :: Python
Classifier: Programming Language :: Python :: 3
Provides-Extra: requests
Provides-Extra: aiohttp
Provides-Extra: grpc
